dolibabyphp/__init__.py
dolibabyphp/__main__.py
dolibabyphp/cli.py
dolibabyphp/exceptions.py
dolibabyphp/exploit.py
dolibabyphp/logging.py
dolibabyphp-1.2.0.dist-info/METADATA
dolibabyphp-1.2.0.dist-info/WHEEL
dolibabyphp-1.2.0.dist-info/entry_points.txt
dolibabyphp-1.2.0.dist-info/licenses/LICENSE
dolibabyphp-1.2.0.dist-info/RECORD
