Metadata-Version: 2.3
Name: dolibabyphp
Version: 1.2.0
Summary: An authenticated RCE exploit for Dolibarr ERP/CRM CVE-2023-30253.
Author-email: Andria Brown <andria_girl@pm.me>
License: MIT License
License-File: LICENSE
Requires-Python: >=3.12
Requires-Dist: bs4>=0.0.2
Requires-Dist: cloup>=3.0.5
Requires-Dist: furl>=2.1.3
Requires-Dist: requests>=2.32.3
Requires-Dist: structlog>=24.2.0
Requires-Dist: tenacity>=8.5.0
Requires-Dist: uuid>=1.30
